survdata.py
survdata/__init__.py
survdata/datasets.py
survdata/metabric.feather
survdata/seer.csv
survdata/support.feather
survival_datasets-0.1.5.dist-info/LICENSE
survival_datasets-0.1.5.dist-info/METADATA
survival_datasets-0.1.5.dist-info/WHEEL
survival_datasets-0.1.5.dist-info/top_level.txt
survival_datasets-0.1.5.dist-info/RECORD
